{
  "siteName": "CHICAGO",
  "eodGroup": "EOD_CHICAGO",
  "zip": "60131",
  "zipPlusFour": "",
  "description": "FSC CHICAGO",
  "permitNumber": "7999",
  "shipperAccount": "4800",
  "mailProducerMid": "901581575",
  "mailProducerCrid": "15345458",
  "sackMailerId": "901581598",
  "sackCrid": "13529793",
  "palletMailerId": "901958885",
  "palletCrid": "15345458",
  "pmodPalletPermitNumber": "24500",
  "alternateCarrierBarcodePrefix": "",
  "isEnabled": true,
  "fullAddress": "FSC CHICAGO 3710 RIVER RD FRANKLIN PARK IL 60131",
  "addressLineOne": "3450 S. 4TH St",
  "addressLineTwo": "",
  "city": "CHICAGO",
  "state": "IL",
  "timeZone": "CENTRAL",
  "uspsPermitNo": "",
  "uspsPaymentMethod": "",
  "uspsPermitNoZip": "",
  "uspsPostageType": "",
  "uspsCsscNo": "",
  "uspsCsscProductNo": "",
  "uspsApiUserId": "535TECMA0117",
  "uspsApiSourceId": "TEC Mailing Solutions, LLC",
  "upsShipperAttentionName": "FSC",
  "upsShipperPhone": "9999999999",
  "evsId": "3",
  "fedExCredentials": {
    "apiKey": "IkjDxnBRabdoIwrDPNVNkrSV3pjIMFqmVcpsH6d3J1M=",
    "apiPassword": "2DiWC25iqbUP59SevWCuXOTCxkOGJ0nhlE/ooP2593E=",
    "accountNumber": "510087100",
    "meterNumber": "114002162"
  },
  "binOverrides": [
    {
      "shippingCarrier": "USPS",
      "shippingMethod": "FIRST_CLASS",
      "binCode": "F65-Z-FC"
    },
    {
      "shippingCarrier": "USPS",
      "shippingMethod": "PRIORITY_MAIL",
      "binCode": "P65-Z-PM"
    },
    {
      "shippingCarrier": "UPS",
      "shippingMethod": "",
      "binCode": "UPS-BIN"
    },
    {
      "shippingCarrier": "FEDEX",
      "shippingMethod": "",
      "binCode": "FEDEX-BIN"
    }
  ],
  "criticalAlertEmailList": [
    "bstabler@tecmailing.com"
  ],
  "criticalAlertSmsList": [],
  "eodSummaryEmailList": [
    "bstabler@tecmailing.com"
  ],
  "siteCustomData": [
    {
      "customDataType": "MERCURYGATE",
      "customData": "GENCO MMS CHICAGO,3710 RIVER RD,,FRANKLIN PARK,IL,60131"
    }
  ],
  "schedules": [],
  "partitionKey": "none",
  "createDate": "2020-10-22T10:56:53.2829461-05:00",
  "isDatasetProcessed": false
}